{"name":"build-javascript","namedChunkGroups":{"polyfill":{"name":"polyfill","assets":[{"name":"webpack-runtime-8b0844c75f66cc3eed4e.js","size":3749},{"name":"polyfill-94f96524d21b228bf347.js","size":83519}],"filteredAssets":0,"assetsSize":87268,"filteredAuxiliaryAssets":2,"auxiliaryAssetsSize":218831},"app":{"name":"app","assets":[{"name":"webpack-runtime-8b0844c75f66cc3eed4e.js","size":3749},{"name":"framework-088290dfd139f338845c.js","size":128717},{"name":"app-f75c31aa87760f67e129.js","size":263760}],"filteredAssets":0,"assetsSize":396226,"filteredAuxiliaryAssets":3,"auxiliaryAssetsSize":1162257},"component---src-templates-docs-js":{"name":"component---src-templates-docs-js","assets":[],"filteredAssets":0,"assetsSize":0,"filteredAuxiliaryAssets":0,"auxiliaryAssetsSize":0}},"assetsByChunkName":{"polyfill":["webpack-runtime-8b0844c75f66cc3eed4e.js","polyfill-94f96524d21b228bf347.js"],"app":["webpack-runtime-8b0844c75f66cc3eed4e.js","framework-088290dfd139f338845c.js","app-f75c31aa87760f67e129.js"],"component---src-templates-docs-js":[]},"childAssetsByChunkName":{}}